cmpal/__init__.py
cmpal/inference/__init__.py
cmpal/inference/llm.py
cmpal/inference/prompts.py
cmpal/main.py
cmpal/models/__init__.py
cmpal/models/config.py
cmpal/scripts/__init__.py
cmpal/scripts/config.py
cmpal/scripts/onboard.py
cmpal/scripts/verify.py
cmpal/utils/format.py
cmpal/utils/git.py
cmpal/utils/terminal.py
cmpal-0.1.7.dist-info/LICENSE
cmpal-0.1.7.dist-info/METADATA
cmpal-0.1.7.dist-info/WHEEL
cmpal-0.1.7.dist-info/entry_points.txt
cmpal-0.1.7.dist-info/RECORD
