Metadata-Version: 2.3
Name: cmpal
Version: 0.1.7
Summary: 
Author: jinyang628
Author-email: chenjinyang4192@gmail.com
Requires-Python: >=3.12, <4.0
Classifier: Programming Language :: Python :: 3
Classifier: Programming Language :: Python :: 3.12
Classifier: Programming Language :: Python :: 3.13
Requires-Dist: colorama (>=0.4.6,<0.5.0)
Requires-Dist: ollama (>=0.4.7,<0.5.0)
Requires-Dist: pydantic (>=2.10.6,<3.0.0)
Requires-Dist: setuptools (>=75.8.0,<76.0.0)
Requires-Dist: simple-term-menu (>=1.6.6,<2.0.0)
